filejack/AsyncDecodeManager.py
filejack/RSC.py
filejack/__init__.py
filejack/conversions.py
filejack/decode_frames.py
filejack/decoder.py
filejack/encoder.py
filejack/merge_frames.py
filejack/reconstruct_data.py
filejack/values.py
filejack-1.0.0rc4.dist-info/METADATA
filejack-1.0.0rc4.dist-info/WHEEL
filejack-1.0.0rc4.dist-info/top_level.txt
filejack-1.0.0rc4.dist-info/RECORD
