Metadata-Version: 2.4
Name: filejack
Version: 1.0.0rc4
Summary: File encoding/decoding to audio signals.
Author: Staheos
Project-URL: Homepage, https://github.com/Staheos/FileJack
Project-URL: Source, https://github.com/Staheos/FileJack
Project-URL: Issues, https://github.com/Staheos/FileJack/issues
Keywords: file,audio,jack,encoder,decoder
Classifier: Development Status :: 3 - Alpha
Classifier: Programming Language :: Python :: 3
Classifier: Programming Language :: Python :: 3 :: Only
Classifier: Programming Language :: Python :: 3.7
Classifier: Programming Language :: Python :: 3.8
Classifier: Programming Language :: Python :: 3.9
Classifier: Programming Language :: Python :: 3.10
Classifier: Programming Language :: Python :: 3.11
Classifier: License :: OSI Approved :: MIT License
Classifier: Operating System :: OS Independent
Requires-Python: >=3.8
Requires-Dist: numpy>=1.15.0
Requires-Dist: scipy>=1.0.0
Requires-Dist: reedsolo>=1.0.0
Provides-Extra: test
Requires-Dist: pytest>=8.0; extra == "test"
Requires-Dist: pytest-cov; extra == "test"
Requires-Dist: pytest-xdist[psutil]>=3.5; extra == "test"
